{
  "cards": [
    {
      "id": "card1",
      "date": "",
      "artist": "The Midnight Crew",
      "song": "",
      "link": "https://open.spotify.com/artist/card1",
      "notes": "🟡",
      "subCards": [
        {
          "category": "other",
          "title": "Dancing in the Dark - OTHER Campaign",
          "goal": "YouTube Marketing + 10K - $375",
          "customGoal": "",
          "subCardDate": "2026-01-17",
          "workflows": [
            {
              "color": "#34c759",
              "letter": "S1"
            },
            {
              "color": "#34c759",
              "letter": "S2"
            },
            {
              "color": "#007aff",
              "letter": "S3"
            },
            {
              "color": "#ffd60a",
              "letter": "S4"
            },
            {
              "color": "#ff3b30",
              "letter": "S5"
            },
            {
              "color": "#ffffff",
              "letter": "MM"
            }
          ],
          "leadNote1": "",
          "leadNote2": "",
          "leadNote3": "",
          "leadNote4": "",
          "leadCheck1": false,
          "leadCheck2": false,
          "leadCheck3": false,
          "leadCheck4": false
        },
        {
          "category": "press",
          "title": "Dancing in the Dark - PRESS Campaign",
          "goal": "SoundCloud + 4K - $180",
          "customGoal": "",
          "subCardDate": "2025-12-29",
          "workflows": [
            {
              "color": "#34c759",
              "letter": "OE"
            },
            {
              "color": "#34c759",
              "letter": "SS"
            },
            {
              "color": "#34c759",
              "letter": "GA"
            },
            {
              "color": "#ffffff",
              "letter": "AP"
            },
            {
              "color": "#ffffff",
              "letter": "PW"
            },
            {
              "color": "#ffd60a",
              "letter": "PG"
            },
            {
              "color": "#34c759",
              "letter": "TR"
            },
            {
              "color": "#ffd60a",
              "letter": "MM"
            }
          ],
          "leadNote1": "",
          "leadNote2": "",
          "leadNote3": "",
          "leadNote4": "",
          "leadCheck1": false,
          "leadCheck2": false,
          "leadCheck3": false,
          "leadCheck4": false
        },
        {
          "category": "social",
          "title": "Ocean Eyes - SOCIAL Campaign",
          "goal": "YouTube Marketing + 10K - $375",
          "customGoal": "",
          "subCardDate": "2026-01-01",
          "workflows": [
            {
              "color": "#ffd60a",
              "letter": "OE"
            },
            {
              "color": "#34c759",
              "letter": "SS"
            },
            {
              "color": "#34c759",
              "letter": "CT"
            },
            {
              "color": "#ffd60a",
              "letter": "DC"
            },
            {
              "color": "#007aff",
              "letter": "PI"
            },
            {
              "color": "#34c759",
              "letter": "TP"
            },
            {
              "color": "#ffffff",
              "letter": "EP"
            },
            {
              "color": "#ffffff",
              "letter": "MM"
            }
          ],
          "leadNote1": "",
          "leadNote2": "",
          "leadNote3": "",
          "leadNote4": "",
          "leadCheck1": false,
          "leadCheck2": false,
          "leadCheck3": false,
          "leadCheck4": false
        },
        {
          "category": "spotify",
          "title": "Sunset Vibes - SPOTIFY Campaign",
          "goal": "YouTube Marketing + 10K - $375",
          "customGoal": "",
          "subCardDate": "2025-12-20",
          "workflows": [
            {
              "color": "#ffd60a",
              "letter": "WU"
            },
            {
              "color": "#ffffff",
              "letter": "OE"
            },
            {
              "color": "#ffd60a",
              "letter": "SS"
            },
            {
              "color": "#34c759",
              "letter": "PI"
            },
            {
              "color": "#34c759",
              "letter": "RD"
            },
            {
              "color": "#34c759",
              "letter": "RL"
            },
            {
              "color": "#ffd60a",
              "letter": "TR"
            },
            {
              "color": "#ffd60a",
              "letter": "MM"
            }
          ],
          "leadNote1": "",
          "leadNote2": "",
          "leadNote3": "",
          "leadNote4": "",
          "leadCheck1": false,
          "leadCheck2": false,
          "leadCheck3": false,
          "leadCheck4": false
        }
      ]
    },
    {
      "id": "card2",
      "date": "",
      "artist": "Luna Eclipse",
      "song": "",
      "link": "https://open.spotify.com/artist/card2",
      "notes": "🟡",
      "subCards": [
        {
          "category": "other",
          "title": "Fireflies - OTHER Campaign",
          "goal": "SoundCloud + 4K - $180",
          "customGoal": "",
          "subCardDate": "2026-01-05",
          "workflows": [
            {
              "color": "#ffffff",
              "letter": "S1"
            },
            {
              "color": "#34c759",
              "letter": "S2"
            },
            {
              "color": "#ffd60a",
              "letter": "S3"
            },
            {
              "color": "#ffd60a",
              "letter": "S4"
            },
            {
              "color": "#ffffff",
              "letter": "S5"
            },
            {
              "color": "#ffd60a",
              "letter": "MM"
            }
          ],
          "leadNote1": "",
          "leadNote2": "",
          "leadNote3": "",
          "leadNote4": "",
          "leadCheck1": false,
          "leadCheck2": false,
          "leadCheck3": false,
          "leadCheck4": false
        },
        {
          "category": "press",
          "title": "Lost in Paradise - PRESS Campaign",
          "goal": "Spotify Playlisting + 10K - $325",
          "customGoal": "",
          "subCardDate": "2025-12-23",
          "workflows": [
            {
              "color": "#ffffff",
              "letter": "OE"
            },
            {
              "color": "#34c759",
              "letter": "SS"
            },
            {
              "color": "#ffd60a",
              "letter": "GA"
            },
            {
              "color": "#34c759",
              "letter": "AP"
            },
            {
              "color": "#34c759",
              "letter": "PW"
            },
            {
              "color": "#ffffff",
              "letter": "PG"
            },
            {
              "color": "#34c759",
              "letter": "TR"
            },
            {
              "color": "#8e44ad",
              "letter": "MM"
            }
          ],
          "leadNote1": "",
          "leadNote2": "",
          "leadNote3": "",
          "leadNote4": "",
          "leadCheck1": false,
          "leadCheck2": false,
          "leadCheck3": false,
          "leadCheck4": false
        },
        {
          "category": "social",
          "title": "Starlight - SOCIAL Campaign",
          "goal": "SoundCloud + 4K - $180",
          "customGoal": "",
          "subCardDate": "2025-12-30",
          "workflows": [
            {
              "color": "#34c759",
              "letter": "OE"
            },
            {
              "color": "#ffffff",
              "letter": "SS"
            },
            {
              "color": "#ffd60a",
              "letter": "CT"
            },
            {
              "color": "#ffffff",
              "letter": "DC"
            },
            {
              "color": "#34c759",
              "letter": "PI"
            },
            {
              "color": "#34c759",
              "letter": "TP"
            },
            {
              "color": "#ffd60a",
              "letter": "EP"
            },
            {
              "color": "#34c759",
              "letter": "MM"
            }
          ],
          "leadNote1": "",
          "leadNote2": "",
          "leadNote3": "",
          "leadNote4": "",
          "leadCheck1": false,
          "leadCheck2": false,
          "leadCheck3": false,
          "leadCheck4": false
        },
        {
          "category": "spotify",
          "title": "Summer Nights - SPOTIFY Campaign",
          "goal": "Spotify Playlisting + 10K - $325",
          "customGoal": "",
          "subCardDate": "2026-01-10",
          "workflows": [
            {
              "color": "#34c759",
              "letter": "WU"
            },
            {
              "color": "#34c759",
              "letter": "OE"
            },
            {
              "color": "#007aff",
              "letter": "SS"
            },
            {
              "color": "#34c759",
              "letter": "PI"
            },
            {
              "color": "#ffd60a",
              "letter": "RD"
            },
            {
              "color": "#34c759",
              "letter": "RL"
            },
            {
              "color": "#34c759",
              "letter": "TR"
            },
            {
              "color": "#ffffff",
              "letter": "MM"
            }
          ],
          "leadNote1": "",
          "leadNote2": "",
          "leadNote3": "",
          "leadNote4": "",
          "leadCheck1": false,
          "leadCheck2": false,
          "leadCheck3": false,
          "leadCheck4": false
        }
      ]
    },
    {
      "id": "card3",
      "date": "",
      "artist": "Digital Dreams",
      "song": "",
      "link": "https://open.spotify.com/artist/card3",
      "notes": "🟡",
      "subCards": [
        {
          "category": "press",
          "title": "City Lights - PRESS Campaign",
          "goal": "Standard Press + 4–7 Articles - $550",
          "customGoal": "",
          "subCardDate": "2025-12-27",
          "workflows": [
            {
              "color": "#ffd60a",
              "letter": "OE"
            },
            {
              "color": "#ffffff",
              "letter": "SS"
            },
            {
              "color": "#007aff",
              "letter": "GA"
            },
            {
              "color": "#34c759",
              "letter": "AP"
            },
            {
              "color": "#ffffff",
              "letter": "PW"
            },
            {
              "color": "#ffffff",
              "letter": "PG"
            },
            {
              "color": "#34c759",
              "letter": "TR"
            },
            {
              "color": "#ffd60a",
              "letter": "MM"
            }
          ],
          "leadNote1": "",
          "leadNote2": "",
          "leadNote3": "",
          "leadNote4": "",
          "leadCheck1": false,
          "leadCheck2": false,
          "leadCheck3": false,
          "leadCheck4": false
        },
        {
          "category": "social",
          "title": "Electric Love - SOCIAL Campaign",
          "goal": "In-Network Press + 3 Articles - $200",
          "customGoal": "",
          "subCardDate": "2026-01-16",
          "workflows": [
            {
              "color": "#ffd60a",
              "letter": "OE"
            },
            {
              "color": "#34c759",
              "letter": "SS"
            },
            {
              "color": "#34c759",
              "letter": "CT"
            },
            {
              "color": "#ffffff",
              "letter": "DC"
            },
            {
              "color": "#34c759",
              "letter": "PI"
            },
            {
              "color": "#34c759",
              "letter": "TP"
            },
            {
              "color": "#ffffff",
              "letter": "EP"
            },
            {
              "color": "#ffd60a",
              "letter": "MM"
            }
          ],
          "leadNote1": "",
          "leadNote2": "",
          "leadNote3": "",
          "leadNote4": "",
          "leadCheck1": false,
          "leadCheck2": false,
          "leadCheck3": false,
          "leadCheck4": false
        },
        {
          "category": "spotify",
          "title": "Electric Love - SPOTIFY Campaign",
          "goal": "Spotify Playlisting + 10K - $325",
          "customGoal": "",
          "subCardDate": "2026-01-01",
          "workflows": [
            {
              "color": "#34c759",
              "letter": "WU"
            },
            {
              "color": "#34c759",
              "letter": "OE"
            },
            {
              "color": "#007aff",
              "letter": "SS"
            },
            {
              "color": "#ffd60a",
              "letter": "PI"
            },
            {
              "color": "#34c759",
              "letter": "RD"
            },
            {
              "color": "#ffd60a",
              "letter": "RL"
            },
            {
              "color": "#ffd60a",
              "letter": "TR"
            },
            {
              "color": "#ffffff",
              "letter": "MM"
            }
          ],
          "leadNote1": "",
          "leadNote2": "",
          "leadNote3": "",
          "leadNote4": "",
          "leadCheck1": false,
          "leadCheck2": false,
          "leadCheck3": false,
          "leadCheck4": false
        },
        {
          "category": "other",
          "title": "Summer Nights - OTHER Campaign",
          "goal": "SoundCloud + 4K - $180",
          "customGoal": "",
          "subCardDate": "2025-12-27",
          "workflows": [
            {
              "color": "#ffd60a",
              "letter": "S1"
            },
            {
              "color": "#ffffff",
              "letter": "S2"
            },
            {
              "color": "#007aff",
              "letter": "S3"
            },
            {
              "color": "#ffffff",
              "letter": "S4"
            },
            {
              "color": "#ffd60a",
              "letter": "S5"
            },
            {
              "color": "#34c759",
              "letter": "MM"
            }
          ],
          "leadNote1": "",
          "leadNote2": "",
          "leadNote3": "",
          "leadNote4": "",
          "leadCheck1": false,
          "leadCheck2": false,
          "leadCheck3": false,
          "leadCheck4": false
        }
      ]
    },
    {
      "id": "card4",
      "date": "",
      "artist": "Neon Waves",
      "song": "",
      "link": "https://open.spotify.com/artist/card4",
      "notes": "🟡",
      "subCards": [
        {
          "category": "press",
          "title": "Heartbreak Avenue - PRESS Campaign",
          "goal": "YouTube Marketing + 10K - $375",
          "customGoal": "",
          "subCardDate": "2026-01-01",
          "workflows": [
            {
              "color": "#ffd60a",
              "letter": "OE"
            },
            {
              "color": "#ffffff",
              "letter": "SS"
            },
            {
              "color": "#34c759",
              "letter": "GA"
            },
            {
              "color": "#ffd60a",
              "letter": "AP"
            },
            {
              "color": "#ffd60a",
              "letter": "PW"
            },
            {
              "color": "#ffd60a",
              "letter": "PG"
            },
            {
              "color": "#ffd60a",
              "letter": "TR"
            },
            {
              "color": "#ffffff",
              "letter": "MM"
            }
          ],
          "leadNote1": "",
          "leadNote2": "",
          "leadNote3": "",
          "leadNote4": "",
          "leadCheck1": false,
          "leadCheck2": false,
          "leadCheck3": false,
          "leadCheck4": false
        },
        {
          "category": "social",
          "title": "Lost in Paradise - SOCIAL Campaign",
          "goal": "In-Network Press + 3 Articles - $200",
          "customGoal": "",
          "subCardDate": "2026-01-09",
          "workflows": [
            {
              "color": "#ffd60a",
              "letter": "OE"
            },
            {
              "color": "#34c759",
              "letter": "SS"
            },
            {
              "color": "#ffffff",
              "letter": "CT"
            },
            {
              "color": "#ffffff",
              "letter": "DC"
            },
            {
              "color": "#ffffff",
              "letter": "PI"
            },
            {
              "color": "#ff3b30",
              "letter": "TP"
            },
            {
              "color": "#ffd60a",
              "letter": "EP"
            },
            {
              "color": "#ff3b30",
              "letter": "MM"
            }
          ],
          "leadNote1": "",
          "leadNote2": "",
          "leadNote3": "",
          "leadNote4": "",
          "leadCheck1": false,
          "leadCheck2": false,
          "leadCheck3": false,
          "leadCheck4": false
        },
        {
          "category": "other",
          "title": "Summer Nights - OTHER Campaign",
          "goal": "Premium Press + 3 Articles - $500",
          "customGoal": "",
          "subCardDate": "2026-01-14",
          "workflows": [
            {
              "color": "#34c759",
              "letter": "S1"
            },
            {
              "color": "#34c759",
              "letter": "S2"
            },
            {
              "color": "#007aff",
              "letter": "S3"
            },
            {
              "color": "#ffd60a",
              "letter": "S4"
            },
            {
              "color": "#ffffff",
              "letter": "S5"
            },
            {
              "color": "#ffffff",
              "letter": "MM"
            }
          ],
          "leadNote1": "",
          "leadNote2": "",
          "leadNote3": "",
          "leadNote4": "",
          "leadCheck1": false,
          "leadCheck2": false,
          "leadCheck3": false,
          "leadCheck4": false
        },
        {
          "category": "spotify",
          "title": "Summer Nights - SPOTIFY Campaign",
          "goal": "SoundCloud + 4K - $180",
          "customGoal": "",
          "subCardDate": "2025-12-31",
          "workflows": [
            {
              "color": "#34c759",
              "letter": "WU"
            },
            {
              "color": "#ffffff",
              "letter": "OE"
            },
            {
              "color": "#007aff",
              "letter": "SS"
            },
            {
              "color": "#34c759",
              "letter": "PI"
            },
            {
              "color": "#34c759",
              "letter": "RD"
            },
            {
              "color": "#ff3b30",
              "letter": "RL"
            },
            {
              "color": "#ffd60a",
              "letter": "TR"
            },
            {
              "color": "#34c759",
              "letter": "MM"
            }
          ],
          "leadNote1": "",
          "leadNote2": "",
          "leadNote3": "",
          "leadNote4": "",
          "leadCheck1": false,
          "leadCheck2": false,
          "leadCheck3": false,
          "leadCheck4": false
        }
      ]
    },
    {
      "id": "card5",
      "date": "",
      "artist": "Echo Chamber",
      "song": "",
      "link": "https://open.spotify.com/artist/card5",
      "notes": "🟡",
      "subCards": [
        {
          "category": "other",
          "title": "Electric Love - OTHER Campaign",
          "goal": "Spotify Playlisting + 10K - $325",
          "customGoal": "",
          "subCardDate": "2026-01-05",
          "workflows": [
            {
              "color": "#ffffff",
              "letter": "S1"
            },
            {
              "color": "#34c759",
              "letter": "S2"
            },
            {
              "color": "#34c759",
              "letter": "S3"
            },
            {
              "color": "#ffd60a",
              "letter": "S4"
            },
            {
              "color": "#ffffff",
              "letter": "S5"
            },
            {
              "color": "#ffffff",
              "letter": "MM"
            }
          ],
          "leadNote1": "",
          "leadNote2": "",
          "leadNote3": "",
          "leadNote4": "",
          "leadCheck1": false,
          "leadCheck2": false,
          "leadCheck3": false,
          "leadCheck4": false
        },
        {
          "category": "social",
          "title": "Lost in Paradise - SOCIAL Campaign",
          "goal": "In-Network Press + 3 Articles - $200",
          "customGoal": "",
          "subCardDate": "2025-12-23",
          "workflows": [
            {
              "color": "#34c759",
              "letter": "OE"
            },
            {
              "color": "#ffffff",
              "letter": "SS"
            },
            {
              "color": "#ffffff",
              "letter": "CT"
            },
            {
              "color": "#ffffff",
              "letter": "DC"
            },
            {
              "color": "#ffffff",
              "letter": "PI"
            },
            {
              "color": "#34c759",
              "letter": "TP"
            },
            {
              "color": "#ffffff",
              "letter": "EP"
            },
            {
              "color": "#ffd60a",
              "letter": "MM"
            }
          ],
          "leadNote1": "",
          "leadNote2": "",
          "leadNote3": "",
          "leadNote4": "",
          "leadCheck1": false,
          "leadCheck2": false,
          "leadCheck3": false,
          "leadCheck4": false
        },
        {
          "category": "spotify",
          "title": "Ocean Eyes - SPOTIFY Campaign",
          "goal": "SoundCloud + 4K - $180",
          "customGoal": "",
          "subCardDate": "2026-01-12",
          "workflows": [
            {
              "color": "#34c759",
              "letter": "WU"
            },
            {
              "color": "#34c759",
              "letter": "OE"
            },
            {
              "color": "#007aff",
              "letter": "SS"
            },
            {
              "color": "#34c759",
              "letter": "PI"
            },
            {
              "color": "#ff3b30",
              "letter": "RD"
            },
            {
              "color": "#34c759",
              "letter": "RL"
            },
            {
              "color": "#34c759",
              "letter": "TR"
            },
            {
              "color": "#34c759",
              "letter": "MM"
            }
          ],
          "leadNote1": "",
          "leadNote2": "",
          "leadNote3": "",
          "leadNote4": "",
          "leadCheck1": false,
          "leadCheck2": false,
          "leadCheck3": false,
          "leadCheck4": false
        },
        {
          "category": "press",
          "title": "Starlight - PRESS Campaign",
          "goal": "Standard Press + 4–7 Articles - $550",
          "customGoal": "",
          "subCardDate": "2025-12-24",
          "workflows": [
            {
              "color": "#ffd60a",
              "letter": "OE"
            },
            {
              "color": "#007aff",
              "letter": "SS"
            },
            {
              "color": "#34c759",
              "letter": "GA"
            },
            {
              "color": "#ffd60a",
              "letter": "AP"
            },
            {
              "color": "#ffffff",
              "letter": "PW"
            },
            {
              "color": "#ffffff",
              "letter": "PG"
            },
            {
              "color": "#ffd60a",
              "letter": "TR"
            },
            {
              "color": "#34c759",
              "letter": "MM"
            }
          ],
          "leadNote1": "",
          "leadNote2": "",
          "leadNote3": "",
          "leadNote4": "",
          "leadCheck1": false,
          "leadCheck2": false,
          "leadCheck3": false,
          "leadCheck4": false
        },
        {
          "category": "spotify",
          "title": "Summer Nights - SPOTIFY Campaign",
          "goal": "Premium Press + 3 Articles - $500",
          "customGoal": "",
          "subCardDate": "2026-01-04",
          "workflows": [
            {
              "color": "#ffffff",
              "letter": "WU"
            },
            {
              "color": "#34c759",
              "letter": "OE"
            },
            {
              "color": "#34c759",
              "letter": "SS"
            },
            {
              "color": "#34c759",
              "letter": "PI"
            },
            {
              "color": "#34c759",
              "letter": "RD"
            },
            {
              "color": "#34c759",
              "letter": "RL"
            },
            {
              "color": "#34c759",
              "letter": "TR"
            },
            {
              "color": "#8e44ad",
              "letter": "MM"
            }
          ],
          "leadNote1": "",
          "leadNote2": "",
          "leadNote3": "",
          "leadNote4": "",
          "leadCheck1": false,
          "leadCheck2": false,
          "leadCheck3": false,
          "leadCheck4": false
        },
        {
          "category": "press",
          "title": "Sunset Vibes - PRESS Campaign",
          "goal": "Spotify Playlisting + 10K - $325",
          "customGoal": "",
          "subCardDate": "2025-12-24",
          "workflows": [
            {
              "color": "#34c759",
              "letter": "OE"
            },
            {
              "color": "#34c759",
              "letter": "SS"
            },
            {
              "color": "#007aff",
              "letter": "GA"
            },
            {
              "color": "#ffd60a",
              "letter": "AP"
            },
            {
              "color": "#ffd60a",
              "letter": "PW"
            },
            {
              "color": "#8e44ad",
              "letter": "PG"
            },
            {
              "color": "#8e44ad",
              "letter": "TR"
            },
            {
              "color": "#8e44ad",
              "letter": "MM"
            }
          ],
          "leadNote1": "",
          "leadNote2": "",
          "leadNote3": "",
          "leadNote4": "",
          "leadCheck1": false,
          "leadCheck2": false,
          "leadCheck3": false,
          "leadCheck4": false
        }
      ]
    },
    {
      "id": "card6",
      "date": "",
      "artist": "Stellar Vibe",
      "song": "",
      "link": "https://open.spotify.com/artist/card6",
      "notes": "🟡",
      "subCards": [
        {
          "category": "press",
          "title": "Neon Dreams - PRESS Campaign",
          "goal": "Standard Press + 4–7 Articles - $550",
          "customGoal": "",
          "subCardDate": "2026-01-17",
          "workflows": [
            {
              "color": "#34c759",
              "letter": "OE"
            },
            {
              "color": "#34c759",
              "letter": "SS"
            },
            {
              "color": "#ffd60a",
              "letter": "GA"
            },
            {
              "color": "#34c759",
              "letter": "AP"
            },
            {
              "color": "#ffffff",
              "letter": "PW"
            },
            {
              "color": "#ffffff",
              "letter": "PG"
            },
            {
              "color": "#ffd60a",
              "letter": "TR"
            },
            {
              "color": "#ffffff",
              "letter": "MM"
            }
          ],
          "leadNote1": "",
          "leadNote2": "",
          "leadNote3": "",
          "leadNote4": "",
          "leadCheck1": false,
          "leadCheck2": false,
          "leadCheck3": false,
          "leadCheck4": false
        },
        {
          "category": "social",
          "title": "Midnight Drive - SOCIAL Campaign",
          "goal": "Premium Press + 3 Articles - $500",
          "customGoal": "",
          "subCardDate": "2026-01-15",
          "workflows": [
            {
              "color": "#ffd60a",
              "letter": "OE"
            },
            {
              "color": "#ffd60a",
              "letter": "SS"
            },
            {
              "color": "#34c759",
              "letter": "CT"
            },
            {
              "color": "#34c759",
              "letter": "DC"
            },
            {
              "color": "#ffd60a",
              "letter": "PI"
            },
            {
              "color": "#ffd60a",
              "letter": "TP"
            },
            {
              "color": "#ffd60a",
              "letter": "EP"
            },
            {
              "color": "#ffffff",
              "letter": "MM"
            }
          ],
          "leadNote1": "",
          "leadNote2": "",
          "leadNote3": "",
          "leadNote4": "",
          "leadCheck1": false,
          "leadCheck2": false,
          "leadCheck3": false,
          "leadCheck4": false
        },
        {
          "category": "spotify",
          "title": "Summer Nights - SPOTIFY Campaign",
          "goal": "Spotify Playlisting + 10K - $325",
          "customGoal": "",
          "subCardDate": "2026-01-13",
          "workflows": [
            {
              "color": "#ffd60a",
              "letter": "WU"
            },
            {
              "color": "#007aff",
              "letter": "OE"
            },
            {
              "color": "#007aff",
              "letter": "SS"
            },
            {
              "color": "#007aff",
              "letter": "PI"
            },
            {
              "color": "#ffffff",
              "letter": "RD"
            },
            {
              "color": "#ffffff",
              "letter": "RL"
            },
            {
              "color": "#ffd60a",
              "letter": "TR"
            },
            {
              "color": "#ffffff",
              "letter": "MM"
            }
          ],
          "leadNote1": "",
          "leadNote2": "",
          "leadNote3": "",
          "leadNote4": "",
          "leadCheck1": false,
          "leadCheck2": false,
          "leadCheck3": false,
          "leadCheck4": false
        },
        {
          "category": "spotify",
          "title": "Heartbreak Avenue - SPOTIFY Campaign",
          "goal": "Premium Press + 3 Articles - $500",
          "customGoal": "",
          "subCardDate": "2026-01-08",
          "workflows": [
            {
              "color": "#007aff",
              "letter": "WU"
            },
            {
              "color": "#ffd60a",
              "letter": "OE"
            },
            {
              "color": "#34c759",
              "letter": "SS"
            },
            {
              "color": "#34c759",
              "letter": "PI"
            },
            {
              "color": "#ffffff",
              "letter": "RD"
            },
            {
              "color": "#ffd60a",
              "letter": "RL"
            },
            {
              "color": "#ff3b30",
              "letter": "TR"
            },
            {
              "color": "#ffd60a",
              "letter": "MM"
            }
          ],
          "leadNote1": "",
          "leadNote2": "",
          "leadNote3": "",
          "leadNote4": "",
          "leadCheck1": false,
          "leadCheck2": false,
          "leadCheck3": false,
          "leadCheck4": false
        },
        {
          "category": "other",
          "title": "Dancing in the Dark - OTHER Campaign",
          "goal": "Standard Press + 4–7 Articles - $550",
          "customGoal": "",
          "subCardDate": "2026-01-08",
          "workflows": [
            {
              "color": "#ffd60a",
              "letter": "S1"
            },
            {
              "color": "#34c759",
              "letter": "S2"
            },
            {
              "color": "#34c759",
              "letter": "S3"
            },
            {
              "color": "#8e44ad",
              "letter": "S4"
            },
            {
              "color": "#ffd60a",
              "letter": "S5"
            },
            {
              "color": "#ffffff",
              "letter": "MM"
            }
          ],
          "leadNote1": "",
          "leadNote2": "",
          "leadNote3": "",
          "leadNote4": "",
          "leadCheck1": false,
          "leadCheck2": false,
          "leadCheck3": false,
          "leadCheck4": false
        }
      ]
    },
    {
      "id": "card7",
      "date": "",
      "artist": "Urban Legends",
      "song": "",
      "link": "https://open.spotify.com/artist/card7",
      "notes": "🟡",
      "subCards": [
        {
          "category": "press",
          "title": "Heartbreak Avenue - PRESS Campaign",
          "goal": "Standard Press + 4–7 Articles - $550",
          "customGoal": "",
          "subCardDate": "2026-01-11",
          "workflows": [
            {
              "color": "#ffffff",
              "letter": "OE"
            },
            {
              "color": "#ffd60a",
              "letter": "SS"
            },
            {
              "color": "#34c759",
              "letter": "GA"
            },
            {
              "color": "#34c759",
              "letter": "AP"
            },
            {
              "color": "#ffffff",
              "letter": "PW"
            },
            {
              "color": "#ffd60a",
              "letter": "PG"
            },
            {
              "color": "#ffffff",
              "letter": "TR"
            },
            {
              "color": "#34c759",
              "letter": "MM"
            }
          ],
          "leadNote1": "",
          "leadNote2": "",
          "leadNote3": "",
          "leadNote4": "",
          "leadCheck1": false,
          "leadCheck2": false,
          "leadCheck3": false,
          "leadCheck4": false
        },
        {
          "category": "spotify",
          "title": "City Lights - SPOTIFY Campaign",
          "goal": "SoundCloud + 4K - $180",
          "customGoal": "",
          "subCardDate": "2026-01-05",
          "workflows": [
            {
              "color": "#007aff",
              "letter": "WU"
            },
            {
              "color": "#34c759",
              "letter": "OE"
            },
            {
              "color": "#ffd60a",
              "letter": "SS"
            },
            {
              "color": "#34c759",
              "letter": "PI"
            },
            {
              "color": "#ffd60a",
              "letter": "RD"
            },
            {
              "color": "#ffffff",
              "letter": "RL"
            },
            {
              "color": "#ffd60a",
              "letter": "TR"
            },
            {
              "color": "#ffd60a",
              "letter": "MM"
            }
          ],
          "leadNote1": "",
          "leadNote2": "",
          "leadNote3": "",
          "leadNote4": "",
          "leadCheck1": false,
          "leadCheck2": false,
          "leadCheck3": false,
          "leadCheck4": false
        },
        {
          "category": "spotify",
          "title": "Electric Love - SPOTIFY Campaign",
          "goal": "YouTube Marketing + 10K - $375",
          "customGoal": "",
          "subCardDate": "2025-12-26",
          "workflows": [
            {
              "color": "#34c759",
              "letter": "WU"
            },
            {
              "color": "#34c759",
              "letter": "OE"
            },
            {
              "color": "#34c759",
              "letter": "SS"
            },
            {
              "color": "#34c759",
              "letter": "PI"
            },
            {
              "color": "#ffffff",
              "letter": "RD"
            },
            {
              "color": "#34c759",
              "letter": "RL"
            },
            {
              "color": "#34c759",
              "letter": "TR"
            },
            {
              "color": "#ffd60a",
              "letter": "MM"
            }
          ],
          "leadNote1": "",
          "leadNote2": "",
          "leadNote3": "",
          "leadNote4": "",
          "leadCheck1": false,
          "leadCheck2": false,
          "leadCheck3": false,
          "leadCheck4": false
        },
        {
          "category": "other",
          "title": "City Lights - OTHER Campaign",
          "goal": "Premium Press + 3 Articles - $500",
          "customGoal": "",
          "subCardDate": "2025-12-24",
          "workflows": [
            {
              "color": "#ffd60a",
              "letter": "S1"
            },
            {
              "color": "#ffffff",
              "letter": "S2"
            },
            {
              "color": "#ffd60a",
              "letter": "S3"
            },
            {
              "color": "#ffd60a",
              "letter": "S4"
            },
            {
              "color": "#ffffff",
              "letter": "S5"
            },
            {
              "color": "#34c759",
              "letter": "MM"
            }
          ],
          "leadNote1": "",
          "leadNote2": "",
          "leadNote3": "",
          "leadNote4": "",
          "leadCheck1": false,
          "leadCheck2": false,
          "leadCheck3": false,
          "leadCheck4": false
        },
        {
          "category": "social",
          "title": "Midnight Drive - SOCIAL Campaign",
          "goal": "In-Network Press + 3 Articles - $200",
          "customGoal": "",
          "subCardDate": "2025-12-19",
          "workflows": [
            {
              "color": "#ffd60a",
              "letter": "OE"
            },
            {
              "color": "#ffd60a",
              "letter": "SS"
            },
            {
              "color": "#34c759",
              "letter": "CT"
            },
            {
              "color": "#34c759",
              "letter": "DC"
            },
            {
              "color": "#ff3b30",
              "letter": "PI"
            },
            {
              "color": "#ffffff",
              "letter": "TP"
            },
            {
              "color": "#ffffff",
              "letter": "EP"
            },
            {
              "color": "#34c759",
              "letter": "MM"
            }
          ],
          "leadNote1": "",
          "leadNote2": "",
          "leadNote3": "",
          "leadNote4": "",
          "leadCheck1": false,
          "leadCheck2": false,
          "leadCheck3": false,
          "leadCheck4": false
        }
      ]
    },
    {
      "id": "card8",
      "date": "",
      "artist": "Crystal Method",
      "song": "",
      "link": "https://open.spotify.com/artist/card8",
      "notes": "🟡",
      "subCards": [
        {
          "category": "social",
          "title": "Electric Love - SOCIAL Campaign",
          "goal": "In-Network Press + 3 Articles - $200",
          "customGoal": "",
          "subCardDate": "2026-01-13",
          "workflows": [
            {
              "color": "#34c759",
              "letter": "OE"
            },
            {
              "color": "#ffd60a",
              "letter": "SS"
            },
            {
              "color": "#34c759",
              "letter": "CT"
            },
            {
              "color": "#34c759",
              "letter": "DC"
            },
            {
              "color": "#ffd60a",
              "letter": "PI"
            },
            {
              "color": "#ffd60a",
              "letter": "TP"
            },
            {
              "color": "#ffd60a",
              "letter": "EP"
            },
            {
              "color": "#ffd60a",
              "letter": "MM"
            }
          ],
          "leadNote1": "",
          "leadNote2": "",
          "leadNote3": "",
          "leadNote4": "",
          "leadCheck1": false,
          "leadCheck2": false,
          "leadCheck3": false,
          "leadCheck4": false
        },
        {
          "category": "spotify",
          "title": "Heartbreak Avenue - SPOTIFY Campaign",
          "goal": "SoundCloud + 4K - $180",
          "customGoal": "",
          "subCardDate": "2026-01-04",
          "workflows": [
            {
              "color": "#007aff",
              "letter": "WU"
            },
            {
              "color": "#ffffff",
              "letter": "OE"
            },
            {
              "color": "#34c759",
              "letter": "SS"
            },
            {
              "color": "#34c759",
              "letter": "PI"
            },
            {
              "color": "#ffffff",
              "letter": "RD"
            },
            {
              "color": "#8e44ad",
              "letter": "RL"
            },
            {
              "color": "#ffffff",
              "letter": "TR"
            },
            {
              "color": "#ffffff",
              "letter": "MM"
            }
          ],
          "leadNote1": "",
          "leadNote2": "",
          "leadNote3": "",
          "leadNote4": "",
          "leadCheck1": false,
          "leadCheck2": false,
          "leadCheck3": false,
          "leadCheck4": false
        },
        {
          "category": "spotify",
          "title": "Midnight Drive - SPOTIFY Campaign",
          "goal": "YouTube Marketing + 10K - $375",
          "customGoal": "",
          "subCardDate": "2025-12-27",
          "workflows": [
            {
              "color": "#34c759",
              "letter": "WU"
            },
            {
              "color": "#ffffff",
              "letter": "OE"
            },
            {
              "color": "#ffd60a",
              "letter": "SS"
            },
            {
              "color": "#ffd60a",
              "letter": "PI"
            },
            {
              "color": "#ffd60a",
              "letter": "RD"
            },
            {
              "color": "#ffffff",
              "letter": "RL"
            },
            {
              "color": "#ffffff",
              "letter": "TR"
            },
            {
              "color": "#34c759",
              "letter": "MM"
            }
          ],
          "leadNote1": "",
          "leadNote2": "",
          "leadNote3": "",
          "leadNote4": "",
          "leadCheck1": false,
          "leadCheck2": false,
          "leadCheck3": false,
          "leadCheck4": false
        },
        {
          "category": "other",
          "title": "Heartbreak Avenue - OTHER Campaign",
          "goal": "Spotify Playlisting + 10K - $325",
          "customGoal": "",
          "subCardDate": "2025-12-23",
          "workflows": [
            {
              "color": "#34c759",
              "letter": "S1"
            },
            {
              "color": "#34c759",
              "letter": "S2"
            },
            {
              "color": "#ffd60a",
              "letter": "S3"
            },
            {
              "color": "#ffd60a",
              "letter": "S4"
            },
            {
              "color": "#34c759",
              "letter": "S5"
            },
            {
              "color": "#ffffff",
              "letter": "MM"
            }
          ],
          "leadNote1": "",
          "leadNote2": "",
          "leadNote3": "",
          "leadNote4": "",
          "leadCheck1": false,
          "leadCheck2": false,
          "leadCheck3": false,
          "leadCheck4": false
        },
        {
          "category": "press",
          "title": "Fireflies - PRESS Campaign",
          "goal": "Standard Press + 4–7 Articles - $550",
          "customGoal": "",
          "subCardDate": "2025-12-21",
          "workflows": [
            {
              "color": "#007aff",
              "letter": "OE"
            },
            {
              "color": "#ffd60a",
              "letter": "SS"
            },
            {
              "color": "#007aff",
              "letter": "GA"
            },
            {
              "color": "#34c759",
              "letter": "AP"
            },
            {
              "color": "#ffffff",
              "letter": "PW"
            },
            {
              "color": "#34c759",
              "letter": "PG"
            },
            {
              "color": "#34c759",
              "letter": "TR"
            },
            {
              "color": "#ffd60a",
              "letter": "MM"
            }
          ],
          "leadNote1": "",
          "leadNote2": "",
          "leadNote3": "",
          "leadNote4": "",
          "leadCheck1": false,
          "leadCheck2": false,
          "leadCheck3": false,
          "leadCheck4": false
        }
      ]
    },
    {
      "id": "card9",
      "date": "",
      "artist": "Phoenix Rising",
      "song": "",
      "link": "https://open.spotify.com/artist/card9",
      "notes": "🟡",
      "subCards": [
        {
          "category": "other",
          "title": "Fireflies - OTHER Campaign",
          "goal": "Spotify Playlisting + 10K - $325",
          "customGoal": "",
          "subCardDate": "2026-01-11",
          "workflows": [
            {
              "color": "#34c759",
              "letter": "S1"
            },
            {
              "color": "#ffffff",
              "letter": "S2"
            },
            {
              "color": "#007aff",
              "letter": "S3"
            },
            {
              "color": "#ffd60a",
              "letter": "S4"
            },
            {
              "color": "#34c759",
              "letter": "S5"
            },
            {
              "color": "#ffffff",
              "letter": "MM"
            }
          ],
          "leadNote1": "",
          "leadNote2": "",
          "leadNote3": "",
          "leadNote4": "",
          "leadCheck1": false,
          "leadCheck2": false,
          "leadCheck3": false,
          "leadCheck4": false
        },
        {
          "category": "social",
          "title": "Ocean Eyes - SOCIAL Campaign",
          "goal": "Spotify Playlisting + 25K - $590",
          "customGoal": "",
          "subCardDate": "2026-01-06",
          "workflows": [
            {
              "color": "#007aff",
              "letter": "OE"
            },
            {
              "color": "#34c759",
              "letter": "SS"
            },
            {
              "color": "#007aff",
              "letter": "CT"
            },
            {
              "color": "#ffd60a",
              "letter": "DC"
            },
            {
              "color": "#ffd60a",
              "letter": "PI"
            },
            {
              "color": "#ffffff",
              "letter": "TP"
            },
            {
              "color": "#34c759",
              "letter": "EP"
            },
            {
              "color": "#34c759",
              "letter": "MM"
            }
          ],
          "leadNote1": "",
          "leadNote2": "",
          "leadNote3": "",
          "leadNote4": "",
          "leadCheck1": false,
          "leadCheck2": false,
          "leadCheck3": false,
          "leadCheck4": false
        },
        {
          "category": "spotify",
          "title": "Dancing in the Dark - SPOTIFY Campaign",
          "goal": "YouTube Marketing + 10K - $375",
          "customGoal": "",
          "subCardDate": "2025-12-31",
          "workflows": [
            {
              "color": "#34c759",
              "letter": "WU"
            },
            {
              "color": "#ffd60a",
              "letter": "OE"
            },
            {
              "color": "#34c759",
              "letter": "SS"
            },
            {
              "color": "#34c759",
              "letter": "PI"
            },
            {
              "color": "#34c759",
              "letter": "RD"
            },
            {
              "color": "#ffffff",
              "letter": "RL"
            },
            {
              "color": "#8e44ad",
              "letter": "TR"
            },
            {
              "color": "#ffffff",
              "letter": "MM"
            }
          ],
          "leadNote1": "",
          "leadNote2": "",
          "leadNote3": "",
          "leadNote4": "",
          "leadCheck1": false,
          "leadCheck2": false,
          "leadCheck3": false,
          "leadCheck4": false
        },
        {
          "category": "press",
          "title": "Sunset Vibes - PRESS Campaign",
          "goal": "Standard Press + 4–7 Articles - $550",
          "customGoal": "",
          "subCardDate": "2025-12-29",
          "workflows": [
            {
              "color": "#34c759",
              "letter": "OE"
            },
            {
              "color": "#34c759",
              "letter": "SS"
            },
            {
              "color": "#34c759",
              "letter": "GA"
            },
            {
              "color": "#34c759",
              "letter": "AP"
            },
            {
              "color": "#8e44ad",
              "letter": "PW"
            },
            {
              "color": "#ffffff",
              "letter": "PG"
            },
            {
              "color": "#ffd60a",
              "letter": "TR"
            },
            {
              "color": "#ffffff",
              "letter": "MM"
            }
          ],
          "leadNote1": "",
          "leadNote2": "",
          "leadNote3": "",
          "leadNote4": "",
          "leadCheck1": false,
          "leadCheck2": false,
          "leadCheck3": false,
          "leadCheck4": false
        },
        {
          "category": "spotify",
          "title": "Dancing in the Dark - SPOTIFY Campaign",
          "goal": "Premium Press + 3 Articles - $500",
          "customGoal": "",
          "subCardDate": "2025-12-21",
          "workflows": [
            {
              "color": "#34c759",
              "letter": "WU"
            },
            {
              "color": "#ffd60a",
              "letter": "OE"
            },
            {
              "color": "#34c759",
              "letter": "SS"
            },
            {
              "color": "#34c759",
              "letter": "PI"
            },
            {
              "color": "#ff3b30",
              "letter": "RD"
            },
            {
              "color": "#ffd60a",
              "letter": "RL"
            },
            {
              "color": "#ffffff",
              "letter": "TR"
            },
            {
              "color": "#ffffff",
              "letter": "MM"
            }
          ],
          "leadNote1": "",
          "leadNote2": "",
          "leadNote3": "",
          "leadNote4": "",
          "leadCheck1": false,
          "leadCheck2": false,
          "leadCheck3": false,
          "leadCheck4": false
        },
        {
          "category": "press",
          "title": "Electric Love - PRESS Campaign",
          "goal": "Standard Press + 4–7 Articles - $550",
          "customGoal": "",
          "subCardDate": "2025-12-21",
          "workflows": [
            {
              "color": "#ffd60a",
              "letter": "OE"
            },
            {
              "color": "#ffd60a",
              "letter": "SS"
            },
            {
              "color": "#ffffff",
              "letter": "GA"
            },
            {
              "color": "#34c759",
              "letter": "AP"
            },
            {
              "color": "#ffffff",
              "letter": "PW"
            },
            {
              "color": "#ffffff",
              "letter": "PG"
            },
            {
              "color": "#ffffff",
              "letter": "TR"
            },
            {
              "color": "#34c759",
              "letter": "MM"
            }
          ],
          "leadNote1": "",
          "leadNote2": "",
          "leadNote3": "",
          "leadNote4": "",
          "leadCheck1": false,
          "leadCheck2": false,
          "leadCheck3": false,
          "leadCheck4": false
        }
      ]
    },
    {
      "id": "card10",
      "date": "",
      "artist": "Velvet Thunder",
      "song": "",
      "link": "https://open.spotify.com/artist/card10",
      "notes": "🟡",
      "subCards": [
        {
          "category": "spotify",
          "title": "Sunset Vibes - SPOTIFY Campaign",
          "goal": "Premium Press + 3 Articles - $500",
          "customGoal": "",
          "subCardDate": "2025-12-22",
          "workflows": [
            {
              "color": "#34c759",
              "letter": "WU"
            },
            {
              "color": "#ffffff",
              "letter": "OE"
            },
            {
              "color": "#ffffff",
              "letter": "SS"
            },
            {
              "color": "#34c759",
              "letter": "PI"
            },
            {
              "color": "#ffd60a",
              "letter": "RD"
            },
            {
              "color": "#ffd60a",
              "letter": "RL"
            },
            {
              "color": "#ffd60a",
              "letter": "TR"
            },
            {
              "color": "#ff3b30",
              "letter": "MM"
            }
          ],
          "leadNote1": "",
          "leadNote2": "",
          "leadNote3": "",
          "leadNote4": "",
          "leadCheck1": false,
          "leadCheck2": false,
          "leadCheck3": false,
          "leadCheck4": false
        },
        {
          "category": "press",
          "title": "Dancing in the Dark - PRESS Campaign",
          "goal": "Spotify Playlisting + 10K - $325",
          "customGoal": "",
          "subCardDate": "2025-12-30",
          "workflows": [
            {
              "color": "#ffffff",
              "letter": "OE"
            },
            {
              "color": "#ffd60a",
              "letter": "SS"
            },
            {
              "color": "#34c759",
              "letter": "GA"
            },
            {
              "color": "#34c759",
              "letter": "AP"
            },
            {
              "color": "#34c759",
              "letter": "PW"
            },
            {
              "color": "#ff3b30",
              "letter": "PG"
            },
            {
              "color": "#ffd60a",
              "letter": "TR"
            },
            {
              "color": "#ffffff",
              "letter": "MM"
            }
          ],
          "leadNote1": "",
          "leadNote2": "",
          "leadNote3": "",
          "leadNote4": "",
          "leadCheck1": false,
          "leadCheck2": false,
          "leadCheck3": false,
          "leadCheck4": false
        },
        {
          "category": "social",
          "title": "Neon Dreams - SOCIAL Campaign",
          "goal": "Standard Press + 4–7 Articles - $550",
          "customGoal": "",
          "subCardDate": "2025-12-26",
          "workflows": [
            {
              "color": "#ffd60a",
              "letter": "OE"
            },
            {
              "color": "#ffd60a",
              "letter": "SS"
            },
            {
              "color": "#007aff",
              "letter": "CT"
            },
            {
              "color": "#34c759",
              "letter": "DC"
            },
            {
              "color": "#ffffff",
              "letter": "PI"
            },
            {
              "color": "#007aff",
              "letter": "TP"
            },
            {
              "color": "#ffffff",
              "letter": "EP"
            },
            {
              "color": "#34c759",
              "letter": "MM"
            }
          ],
          "leadNote1": "",
          "leadNote2": "",
          "leadNote3": "",
          "leadNote4": "",
          "leadCheck1": false,
          "leadCheck2": false,
          "leadCheck3": false,
          "leadCheck4": false
        }
      ]
    },
    {
      "id": "card11",
      "date": "",
      "artist": "Arctic Monkeys Cover Band",
      "song": "",
      "link": "https://open.spotify.com/artist/card11",
      "notes": "🟡",
      "subCards": [
        {
          "category": "spotify",
          "title": "City Lights - SPOTIFY Campaign",
          "goal": "Standard Press + 4–7 Articles - $550",
          "customGoal": "",
          "subCardDate": "2025-12-29",
          "workflows": [
            {
              "color": "#34c759",
              "letter": "WU"
            },
            {
              "color": "#34c759",
              "letter": "OE"
            },
            {
              "color": "#34c759",
              "letter": "SS"
            },
            {
              "color": "#ffd60a",
              "letter": "PI"
            },
            {
              "color": "#ffd60a",
              "letter": "RD"
            },
            {
              "color": "#ffd60a",
              "letter": "RL"
            },
            {
              "color": "#34c759",
              "letter": "TR"
            },
            {
              "color": "#34c759",
              "letter": "MM"
            }
          ],
          "leadNote1": "",
          "leadNote2": "",
          "leadNote3": "",
          "leadNote4": "",
          "leadCheck1": false,
          "leadCheck2": false,
          "leadCheck3": false,
          "leadCheck4": false
        },
        {
          "category": "press",
          "title": "Fireflies - PRESS Campaign",
          "goal": "Premium Press + 3 Articles - $500",
          "customGoal": "",
          "subCardDate": "2026-01-07",
          "workflows": [
            {
              "color": "#007aff",
              "letter": "OE"
            },
            {
              "color": "#34c759",
              "letter": "SS"
            },
            {
              "color": "#34c759",
              "letter": "GA"
            },
            {
              "color": "#ffd60a",
              "letter": "AP"
            },
            {
              "color": "#ffffff",
              "letter": "PW"
            },
            {
              "color": "#ff3b30",
              "letter": "PG"
            },
            {
              "color": "#ffd60a",
              "letter": "TR"
            },
            {
              "color": "#ffffff",
              "letter": "MM"
            }
          ],
          "leadNote1": "",
          "leadNote2": "",
          "leadNote3": "",
          "leadNote4": "",
          "leadCheck1": false,
          "leadCheck2": false,
          "leadCheck3": false,
          "leadCheck4": false
        },
        {
          "category": "social",
          "title": "Neon Dreams - SOCIAL Campaign",
          "goal": "Spotify Playlisting + 25K - $590",
          "customGoal": "",
          "subCardDate": "2025-12-29",
          "workflows": [
            {
              "color": "#007aff",
              "letter": "OE"
            },
            {
              "color": "#34c759",
              "letter": "SS"
            },
            {
              "color": "#ffd60a",
              "letter": "CT"
            },
            {
              "color": "#ffd60a",
              "letter": "DC"
            },
            {
              "color": "#ffffff",
              "letter": "PI"
            },
            {
              "color": "#007aff",
              "letter": "TP"
            },
            {
              "color": "#34c759",
              "letter": "EP"
            },
            {
              "color": "#ffd60a",
              "letter": "MM"
            }
          ],
          "leadNote1": "",
          "leadNote2": "",
          "leadNote3": "",
          "leadNote4": "",
          "leadCheck1": false,
          "leadCheck2": false,
          "leadCheck3": false,
          "leadCheck4": false
        },
        {
          "category": "other",
          "title": "Lost in Paradise - OTHER Campaign",
          "goal": "Spotify Playlisting + 10K - $325",
          "customGoal": "",
          "subCardDate": "2026-01-17",
          "workflows": [
            {
              "color": "#34c759",
              "letter": "S1"
            },
            {
              "color": "#007aff",
              "letter": "S2"
            },
            {
              "color": "#34c759",
              "letter": "S3"
            },
            {
              "color": "#ffd60a",
              "letter": "S4"
            },
            {
              "color": "#ffffff",
              "letter": "S5"
            },
            {
              "color": "#007aff",
              "letter": "MM"
            }
          ],
          "leadNote1": "",
          "leadNote2": "",
          "leadNote3": "",
          "leadNote4": "",
          "leadCheck1": false,
          "leadCheck2": false,
          "leadCheck3": false,
          "leadCheck4": false
        },
        {
          "category": "spotify",
          "title": "Electric Love - SPOTIFY Campaign",
          "goal": "Spotify Playlisting + 10K - $325",
          "customGoal": "",
          "subCardDate": "2026-01-15",
          "workflows": [
            {
              "color": "#ffd60a",
              "letter": "WU"
            },
            {
              "color": "#34c759",
              "letter": "OE"
            },
            {
              "color": "#34c759",
              "letter": "SS"
            },
            {
              "color": "#34c759",
              "letter": "PI"
            },
            {
              "color": "#ffffff",
              "letter": "RD"
            },
            {
              "color": "#ffd60a",
              "letter": "RL"
            },
            {
              "color": "#ffd60a",
              "letter": "TR"
            },
            {
              "color": "#ffd60a",
              "letter": "MM"
            }
          ],
          "leadNote1": "",
          "leadNote2": "",
          "leadNote3": "",
          "leadNote4": "",
          "leadCheck1": false,
          "leadCheck2": false,
          "leadCheck3": false,
          "leadCheck4": false
        },
        {
          "category": "press",
          "title": "Midnight Drive - PRESS Campaign",
          "goal": "Standard Press + 4–7 Articles - $550",
          "customGoal": "",
          "subCardDate": "2026-01-01",
          "workflows": [
            {
              "color": "#34c759",
              "letter": "OE"
            },
            {
              "color": "#ffd60a",
              "letter": "SS"
            },
            {
              "color": "#ffd60a",
              "letter": "GA"
            },
            {
              "color": "#34c759",
              "letter": "AP"
            },
            {
              "color": "#34c759",
              "letter": "PW"
            },
            {
              "color": "#34c759",
              "letter": "PG"
            },
            {
              "color": "#ffd60a",
              "letter": "TR"
            },
            {
              "color": "#ffffff",
              "letter": "MM"
            }
          ],
          "leadNote1": "",
          "leadNote2": "",
          "leadNote3": "",
          "leadNote4": "",
          "leadCheck1": false,
          "leadCheck2": false,
          "leadCheck3": false,
          "leadCheck4": false
        }
      ]
    },
    {
      "id": "card12",
      "date": "",
      "artist": "Sunset Boulevard",
      "song": "",
      "link": "https://open.spotify.com/artist/card12",
      "notes": "🟡",
      "subCards": [
        {
          "category": "spotify",
          "title": "Sunset Vibes - SPOTIFY Campaign",
          "goal": "Standard Press + 4–7 Articles - $550",
          "customGoal": "",
          "subCardDate": "2026-01-02",
          "workflows": [
            {
              "color": "#ffffff",
              "letter": "WU"
            },
            {
              "color": "#34c759",
              "letter": "OE"
            },
            {
              "color": "#ffd60a",
              "letter": "SS"
            },
            {
              "color": "#34c759",
              "letter": "PI"
            },
            {
              "color": "#ffffff",
              "letter": "RD"
            },
            {
              "color": "#ffffff",
              "letter": "RL"
            },
            {
              "color": "#34c759",
              "letter": "TR"
            },
            {
              "color": "#ffd60a",
              "letter": "MM"
            }
          ],
          "leadNote1": "",
          "leadNote2": "",
          "leadNote3": "",
          "leadNote4": "",
          "leadCheck1": false,
          "leadCheck2": false,
          "leadCheck3": false,
          "leadCheck4": false
        },
        {
          "category": "press",
          "title": "Starlight - PRESS Campaign",
          "goal": "Spotify Playlisting + 10K - $325",
          "customGoal": "",
          "subCardDate": "2026-01-01",
          "workflows": [
            {
              "color": "#007aff",
              "letter": "OE"
            },
            {
              "color": "#34c759",
              "letter": "SS"
            },
            {
              "color": "#ffd60a",
              "letter": "GA"
            },
            {
              "color": "#ffd60a",
              "letter": "AP"
            },
            {
              "color": "#ffffff",
              "letter": "PW"
            },
            {
              "color": "#007aff",
              "letter": "PG"
            },
            {
              "color": "#ffffff",
              "letter": "TR"
            },
            {
              "color": "#ffd60a",
              "letter": "MM"
            }
          ],
          "leadNote1": "",
          "leadNote2": "",
          "leadNote3": "",
          "leadNote4": "",
          "leadCheck1": false,
          "leadCheck2": false,
          "leadCheck3": false,
          "leadCheck4": false
        },
        {
          "category": "social",
          "title": "Summer Nights - SOCIAL Campaign",
          "goal": "Spotify Playlisting + 25K - $590",
          "customGoal": "",
          "subCardDate": "2026-01-13",
          "workflows": [
            {
              "color": "#34c759",
              "letter": "OE"
            },
            {
              "color": "#007aff",
              "letter": "SS"
            },
            {
              "color": "#007aff",
              "letter": "CT"
            },
            {
              "color": "#34c759",
              "letter": "DC"
            },
            {
              "color": "#34c759",
              "letter": "PI"
            },
            {
              "color": "#ffd60a",
              "letter": "TP"
            },
            {
              "color": "#34c759",
              "letter": "EP"
            },
            {
              "color": "#ffffff",
              "letter": "MM"
            }
          ],
          "leadNote1": "",
          "leadNote2": "",
          "leadNote3": "",
          "leadNote4": "",
          "leadCheck1": false,
          "leadCheck2": false,
          "leadCheck3": false,
          "leadCheck4": false
        },
        {
          "category": "other",
          "title": "Dancing in the Dark - OTHER Campaign",
          "goal": "Standard Press + 4–7 Articles - $550",
          "customGoal": "",
          "subCardDate": "2026-01-05",
          "workflows": [
            {
              "color": "#34c759",
              "letter": "S1"
            },
            {
              "color": "#ffd60a",
              "letter": "S2"
            },
            {
              "color": "#ffffff",
              "letter": "S3"
            },
            {
              "color": "#34c759",
              "letter": "S4"
            },
            {
              "color": "#34c759",
              "letter": "S5"
            },
            {
              "color": "#ffffff",
              "letter": "MM"
            }
          ],
          "leadNote1": "",
          "leadNote2": "",
          "leadNote3": "",
          "leadNote4": "",
          "leadCheck1": false,
          "leadCheck2": false,
          "leadCheck3": false,
          "leadCheck4": false
        }
      ]
    },
    {
      "id": "card13",
      "date": "",
      "artist": "Electric Avenue",
      "song": "",
      "link": "https://open.spotify.com/artist/card13",
      "notes": "🟡",
      "subCards": [
        {
          "category": "spotify",
          "title": "Summer Nights - SPOTIFY Campaign",
          "goal": "Premium Press + 3 Articles - $500",
          "customGoal": "",
          "subCardDate": "2026-01-04",
          "workflows": [
            {
              "color": "#34c759",
              "letter": "WU"
            },
            {
              "color": "#ffd60a",
              "letter": "OE"
            },
            {
              "color": "#34c759",
              "letter": "SS"
            },
            {
              "color": "#34c759",
              "letter": "PI"
            },
            {
              "color": "#ffffff",
              "letter": "RD"
            },
            {
              "color": "#8e44ad",
              "letter": "RL"
            },
            {
              "color": "#ffffff",
              "letter": "TR"
            },
            {
              "color": "#ffffff",
              "letter": "MM"
            }
          ],
          "leadNote1": "",
          "leadNote2": "",
          "leadNote3": "",
          "leadNote4": "",
          "leadCheck1": false,
          "leadCheck2": false,
          "leadCheck3": false,
          "leadCheck4": false
        },
        {
          "category": "press",
          "title": "Fireflies - PRESS Campaign",
          "goal": "Standard Press + 4–7 Articles - $550",
          "customGoal": "",
          "subCardDate": "2025-12-26",
          "workflows": [
            {
              "color": "#ffffff",
              "letter": "OE"
            },
            {
              "color": "#34c759",
              "letter": "SS"
            },
            {
              "color": "#007aff",
              "letter": "GA"
            },
            {
              "color": "#ffd60a",
              "letter": "AP"
            },
            {
              "color": "#ffffff",
              "letter": "PW"
            },
            {
              "color": "#ffffff",
              "letter": "PG"
            },
            {
              "color": "#ffd60a",
              "letter": "TR"
            },
            {
              "color": "#ffd60a",
              "letter": "MM"
            }
          ],
          "leadNote1": "",
          "leadNote2": "",
          "leadNote3": "",
          "leadNote4": "",
          "leadCheck1": false,
          "leadCheck2": false,
          "leadCheck3": false,
          "leadCheck4": false
        },
        {
          "category": "social",
          "title": "Neon Dreams - SOCIAL Campaign",
          "goal": "SoundCloud + 4K - $180",
          "customGoal": "",
          "subCardDate": "2025-12-27",
          "workflows": [
            {
              "color": "#007aff",
              "letter": "OE"
            },
            {
              "color": "#34c759",
              "letter": "SS"
            },
            {
              "color": "#ffd60a",
              "letter": "CT"
            },
            {
              "color": "#ffd60a",
              "letter": "DC"
            },
            {
              "color": "#34c759",
              "letter": "PI"
            },
            {
              "color": "#ffffff",
              "letter": "TP"
            },
            {
              "color": "#ffd60a",
              "letter": "EP"
            },
            {
              "color": "#ffffff",
              "letter": "MM"
            }
          ],
          "leadNote1": "",
          "leadNote2": "",
          "leadNote3": "",
          "leadNote4": "",
          "leadCheck1": false,
          "leadCheck2": false,
          "leadCheck3": false,
          "leadCheck4": false
        },
        {
          "category": "other",
          "title": "Sunset Vibes - OTHER Campaign",
          "goal": "YouTube Marketing + 10K - $375",
          "customGoal": "",
          "subCardDate": "2026-01-13",
          "workflows": [
            {
              "color": "#34c759",
              "letter": "S1"
            },
            {
              "color": "#34c759",
              "letter": "S2"
            },
            {
              "color": "#ffffff",
              "letter": "S3"
            },
            {
              "color": "#ffffff",
              "letter": "S4"
            },
            {
              "color": "#34c759",
              "letter": "S5"
            },
            {
              "color": "#ffffff",
              "letter": "MM"
            }
          ],
          "leadNote1": "",
          "leadNote2": "",
          "leadNote3": "",
          "leadNote4": "",
          "leadCheck1": false,
          "leadCheck2": false,
          "leadCheck3": false,
          "leadCheck4": false
        }
      ]
    },
    {
      "id": "card14",
      "date": "",
      "artist": "Cosmic Dust",
      "song": "",
      "link": "",
      "notes": "🟡",
      "subCards": [
        {
          "category": "spotify",
          "title": "Heartbreak Avenue - New Release",
          "goal": "Spotify Playlisting + 25K - $590",
          "customGoal": "",
          "subCardDate": "2025-12-23",
          "workflows": [
            {
              "color": "#ffffff",
              "letter": "WU"
            },
            {
              "color": "#ffffff",
              "letter": "OE"
            },
            {
              "color": "#ffffff",
              "letter": "SS"
            },
            {
              "color": "#ffffff",
              "letter": "PI"
            },
            {
              "color": "#ffffff",
              "letter": "RD"
            },
            {
              "color": "#ffffff",
              "letter": "RL"
            },
            {
              "color": "#ffffff",
              "letter": "TR"
            },
            {
              "color": "#ffffff",
              "letter": "MM"
            }
          ],
          "leadNote1": "",
          "leadNote2": "",
          "leadNote3": "",
          "leadNote4": "",
          "leadCheck1": false,
          "leadCheck2": false,
          "leadCheck3": false,
          "leadCheck4": false
        },
        {
          "category": "press",
          "title": "Neon Dreams - New Release",
          "goal": "YouTube Marketing + 10K - $375",
          "customGoal": "",
          "subCardDate": "2025-12-30",
          "workflows": [
            {
              "color": "#ffffff",
              "letter": "OE"
            },
            {
              "color": "#ffffff",
              "letter": "SS"
            },
            {
              "color": "#ffffff",
              "letter": "GA"
            },
            {
              "color": "#ffffff",
              "letter": "AP"
            },
            {
              "color": "#ffffff",
              "letter": "PW"
            },
            {
              "color": "#ffffff",
              "letter": "PG"
            },
            {
              "color": "#ffffff",
              "letter": "TR"
            },
            {
              "color": "#ffffff",
              "letter": "MM"
            }
          ],
          "leadNote1": "",
          "leadNote2": "",
          "leadNote3": "",
          "leadNote4": "",
          "leadCheck1": false,
          "leadCheck2": false,
          "leadCheck3": false,
          "leadCheck4": false
        },
        {
          "category": "spotify",
          "title": "City Lights - New Release",
          "goal": "Spotify Playlisting + 25K - $590",
          "customGoal": "",
          "subCardDate": "2026-01-06",
          "workflows": [
            {
              "color": "#ffffff",
              "letter": "WU"
            },
            {
              "color": "#ffffff",
              "letter": "OE"
            },
            {
              "color": "#ffffff",
              "letter": "SS"
            },
            {
              "color": "#ffffff",
              "letter": "PI"
            },
            {
              "color": "#ffffff",
              "letter": "RD"
            },
            {
              "color": "#ffffff",
              "letter": "RL"
            },
            {
              "color": "#ffffff",
              "letter": "TR"
            },
            {
              "color": "#ffffff",
              "letter": "MM"
            }
          ],
          "leadNote1": "",
          "leadNote2": "",
          "leadNote3": "",
          "leadNote4": "",
          "leadCheck1": false,
          "leadCheck2": false,
          "leadCheck3": false,
          "leadCheck4": false
        }
      ]
    }
  ],
  "cardCounter": 14,
  "parentFolders": {
    "parent1": {
      "name": "Major Label Artists",
      "cards": [
        "card1",
        "card2",
        "card3",
        "card4",
        "card5"
      ]
    },
    "parent2": {
      "name": "Independent Artists",
      "cards": [
        "card6",
        "card7",
        "card8",
        "card9"
      ]
    },
    "parent3": {
      "name": "Rising Stars",
      "cards": [
        "card10",
        "card11",
        "card12",
        "card13"
      ]
    }
  },
  "parentFolderCounter": 3,
  "cardParentMap": {
    "card1": "parent1",
    "card2": "parent1",
    "card3": "parent1",
    "card4": "parent1",
    "card5": "parent1",
    "card6": "parent2",
    "card7": "parent2",
    "card8": "parent2",
    "card9": "parent2",
    "card10": "parent3",
    "card11": "parent3",
    "card12": "parent3",
    "card13": "parent3"
  }
}